LICENSE
MANIFEST.in
README.md
setup.py
extra_keras_metrics/__init__.py
extra_keras_metrics/__version__.py
extra_keras_metrics/balanced_accuracy.py
extra_keras_metrics/binary_metric.py
extra_keras_metrics/diagnostic_odds_ratio.py
extra_keras_metrics/f1score.py
extra_keras_metrics/fallout.py
extra_keras_metrics/false_discovery_rate.py
extra_keras_metrics/false_negatives_ratio.py
extra_keras_metrics/false_omission_rate.py
extra_keras_metrics/false_positives_ratio.py
extra_keras_metrics/fowlkes_mallows_index.py
extra_keras_metrics/get_binary_metrics.py
extra_keras_metrics/informedness.py
extra_keras_metrics/markedness.py
extra_keras_metrics/matthews_correlation_coefficient.py
extra_keras_metrics/miss_rate.py
extra_keras_metrics/negative_likelihood_ratio.py
extra_keras_metrics/negative_predictive_value.py
extra_keras_metrics/positive_likelihood_ratio.py
extra_keras_metrics/prevalence_threshold.py
extra_keras_metrics/py.typed
extra_keras_metrics/specificity.py
extra_keras_metrics/threat_score.py
extra_keras_metrics/true_negatives_ratio.py
extra_keras_metrics/true_positives_ratio.py
extra_keras_metrics.egg-info/PKG-INFO
extra_keras_metrics.egg-info/SOURCES.txt
extra_keras_metrics.egg-info/dependency_links.txt
extra_keras_metrics.egg-info/requires.txt
extra_keras_metrics.egg-info/top_level.txt