Metadata-Version: 2.1
Name: extra-keras-metrics
Version: 2.0.14
Summary: Additional metrics integrated with the TensorFlow and Keras NN library.
Home-page: https://github.com/LucaCappelletti94/extra_keras_metrics
Author: Luca Cappelletti
Author-email: cappelletti.luca94@gmail.com
License: MIT
Platform: UNKNOWN
Classifier: Development Status :: 5 - Production/Stable
Classifier: License :: OSI Approved :: MIT License
Classifier: Programming Language :: Python :: 3
Provides-Extra: test
License-File: LICENSE
